[{"name":"D:\\FXServer\\youtube\\resources\\[gameplay]\\chat\\html\\index.html","stats":{"mtime":1634727000000,"size":391,"inode":1125899906884497}},{"name":"D:\\FXServer\\youtube\\resources\\[gameplay]\\chat\\node_modules\\lodash\\lodash.js","stats":{"mtime":1650228312000,"size":540512,"inode":1125899906900700}},{"name":"D:\\FXServer\\youtube\\resources\\[system]\\[builders]\\webpack\\node_modules\\webpack\\buildin\\global.js","stats":{"mtime":1650228304000,"size":472,"inode":562949953494009}},{"name":"D:\\FXServer\\youtube\\resources\\[system]\\[builders]\\webpack\\node_modules\\webpack\\buildin\\module.js","stats":{"mtime":1650228304000,"size":497,"inode":562949953494011}},{"name":"D:\\FXServer\\youtube\\resources\\[gameplay]\\chat\\html\\App.ts","stats":{"mtime":1634727000000,"size":13445,"inode":1125899906884464}},{"name":"D:\\FXServer\\youtube\\resources\\[gameplay]\\chat\\html\\App.vue","stats":{"mtime":1634727000000,"size":1544,"inode":1125899906884467}},{"name":"D:\\FXServer\\youtube\\resources\\[gameplay]\\chat\\html\\Message.ts","stats":{"mtime":1634727000000,"size":3273,"inode":1125899906884518}},{"name":"D:\\FXServer\\youtube\\resources\\[gameplay]\\chat\\html\\Message.vue","stats":{"mtime":1634727000000,"size":167,"inode":1125899906884519}},{"name":"D:\\FXServer\\youtube\\resources\\[gameplay]\\chat\\html\\Suggestions.ts","stats":{"mtime":1634727000000,"size":1696,"inode":1125899906884520}},{"name":"D:\\FXServer\\youtube\\resources\\[gameplay]\\chat\\html\\Suggestions.vue","stats":{"mtime":1634727000000,"size":909,"inode":1125899906884524}},{"name":"D:\\FXServer\\youtube\\resources\\[gameplay]\\chat\\html\\config.ts","stats":{"mtime":1634727000000,"size":479,"inode":1125899906884486}},{"name":"D:\\FXServer\\youtube\\resources\\[gameplay]\\chat\\html\\index.d.ts","stats":{"mtime":1634727000000,"size":75,"inode":1125899906884495}},{"name":"D:\\FXServer\\youtube\\resources\\[gameplay]\\chat\\html\\index.html","stats":{"mtime":1634727000000,"size":391,"inode":1125899906884497}},{"name":"D:\\FXServer\\youtube\\resources\\[gameplay]\\chat\\html\\main.ts","stats":{"mtime":1634727000000,"size":124,"inode":1125899906884505}},{"name":"D:\\FXServer\\youtube\\resources\\[gameplay]\\chat\\html\\utils.ts","stats":{"mtime":1634727000000,"size":685,"inode":1125899906884529}},{"name":"D:\\FXServer\\youtube\\resources\\[gameplay]\\chat\\node_modules\\@types\\events\\index.d.ts","stats":{"mtime":1650228322000,"size":1273,"inode":1125899906885029}},{"name":"D:\\FXServer\\youtube\\resources\\[gameplay]\\chat\\node_modules\\@types\\glob\\index.d.ts","stats":{"mtime":1650228322000,"size":3053,"inode":1125899906885094}},{"name":"D:\\FXServer\\youtube\\resources\\[gameplay]\\chat\\node_modules\\@types\\minimatch\\index.d.ts","stats":{"mtime":1650228322000,"size":5588,"inode":1125899906885117}},{"name":"D:\\FXServer\\youtube\\resources\\[gameplay]\\chat\\node_modules\\@types\\node\\assert.d.ts","stats":{"mtime":1650228322000,"size":2910,"inode":1125899906885123}},{"name":"D:\\FXServer\\youtube\\resources\\[gameplay]\\chat\\node_modules\\@types\\node\\async_hooks.d.ts","stats":{"mtime":1650228322000,"size":10846,"inode":1125899906885124}},{"name":"D:\\FXServer\\youtube\\resources\\[gameplay]\\chat\\node_modules\\@types\\node\\base.d.ts","stats":{"mtime":1650228322000,"size":1588,"inode":1125899906885125}},{"name":"D:\\FXServer\\youtube\\resources\\[gameplay]\\chat\\node_modules\\@types\\node\\buffer.d.ts","stats":{"mtime":1650228322000,"size":706,"inode":1125899906885127}},{"name":"D:\\FXServer\\youtube\\resources\\[gameplay]\\chat\\node_modules\\@types\\node\\child_process.d.ts","stats":{"mtime":1650228322000,"size":24552,"inode":1125899906885128}},{"name":"D:\\FXServer\\youtube\\resources\\[gameplay]\\chat\\node_modules\\@types\\node\\cluster.d.ts","stats":{"mtime":1650228322000,"size":16197,"inode":1125899906885130}},{"name":"D:\\FXServer\\youtube\\resources\\[gameplay]\\chat\\node_modules\\@types\\node\\console.d.ts","stats":{"mtime":1650228322000,"size":51,"inode":1125899906885131}},{"name":"D:\\FXServer\\youtube\\resources\\[gameplay]\\chat\\node_modules\\@types\\node\\constants.d.ts","stats":{"mtime":1650228322000,"size":459,"inode":1125899906885132}},{"name":"D:\\FXServer\\youtube\\resources\\[gameplay]\\chat\\node_modules\\@types\\node\\crypto.d.ts","stats":{"mtime":1650228322000,"size":30570,"inode":1125899906885139}},{"name":"D:\\FXServer\\youtube\\resources\\[gameplay]\\chat\\node_modules\\@types\\node\\dgram.d.ts","stats":{"mtime":1650228322000,"size":7156,"inode":1125899906885146}},{"name":"D:\\FXServer\\youtube\\resources\\[gameplay]\\chat\\node_modules\\@types\\node\\dns.d.ts","stats":{"mtime":1650228322000,"size":16002,"inode":1125899906885147}},{"name":"D:\\FXServer\\youtube\\resources\\[gameplay]\\chat\\node_modules\\@types\\node\\domain.d.ts","stats":{"mtime":1650228322000,"size":545,"inode":1125899906885148}},{"name":"D:\\FXServer\\youtube\\resources\\[gameplay]\\chat\\node_modules\\@types\\node\\events.d.ts","stats":{"mtime":1650228322000,"size":1841,"inode":1125899906885152}},{"name":"D:\\FXServer\\youtube\\resources\\[gameplay]\\chat\\node_modules\\@types\\node\\fs.d.ts","stats":{"mtime":1650228322000,"size":140811,"inode":1125899906885153}},{"name":"D:\\FXServer\\youtube\\resources\\[gameplay]\\chat\\node_modules\\@types\\node\\globals.d.ts","stats":{"mtime":1650228322000,"size":45295,"inode":1125899906885154}},{"name":"D:\\FXServer\\youtube\\resources\\[gameplay]\\chat\\node_modules\\@types\\node\\http.d.ts","stats":{"mtime":1650228322000,"size":17738,"inode":1125899906885155}},{"name":"D:\\FXServer\\youtube\\resources\\[gameplay]\\chat\\node_modules\\@types\\node\\http2.d.ts","stats":{"mtime":1650228322000,"size":56307,"inode":1125899906885156}},{"name":"D:\\FXServer\\youtube\\resources\\[gameplay]\\chat\\node_modules\\@types\\node\\https.d.ts","stats":{"mtime":1650228322000,"size":1684,"inode":1125899906885158}},{"name":"D:\\FXServer\\youtube\\resources\\[gameplay]\\chat\\node_modules\\@types\\node\\inspector.d.ts","stats":{"mtime":1650228322000,"size":121692,"inode":1125899906885161}},{"name":"D:\\FXServer\\youtube\\resources\\[gameplay]\\chat\\node_modules\\@types\\node\\module.d.ts","stats":{"mtime":1650228322000,"size":1741,"inode":1125899906885163}},{"name":"D:\\FXServer\\youtube\\resources\\[gameplay]\\chat\\node_modules\\@types\\node\\net.d.ts","stats":{"mtime":1650228322000,"size":12804,"inode":1125899906885164}},{"name":"D:\\FXServer\\youtube\\resources\\[gameplay]\\chat\\node_modules\\@types\\node\\os.d.ts","stats":{"mtime":1650228322000,"size":8178,"inode":1125899906885165}},{"name":"D:\\FXServer\\youtube\\resources\\[gameplay]\\chat\\node_modules\\@types\\node\\path.d.ts","stats":{"mtime":1650228322000,"size":6309,"inode":1125899906885167}},{"name":"D:\\FXServer\\youtube\\resources\\[gameplay]\\chat\\node_modules\\@types\\node\\perf_hooks.d.ts","stats":{"mtime":1650228322000,"size":12044,"inode":1125899906885168}},{"name":"D:\\FXServer\\youtube\\resources\\[gameplay]\\chat\\node_modules\\@types\\node\\process.d.ts","stats":{"mtime":1650228322000,"size":517,"inode":1125899906885169}},{"name":"D:\\FXServer\\youtube\\resources\\[gameplay]\\chat\\node_modules\\@types\\node\\punycode.d.ts","stats":{"mtime":1650228322000,"size":378,"inode":1125899906885170}},{"name":"D:\\FXServer\\youtube\\resources\\[gameplay]\\chat\\node_modules\\@types\\node\\querystring.d.ts","stats":{"mtime":1650228322000,"size":1017,"inode":1125899906885171}},{"name":"D:\\FXServer\\youtube\\resources\\[gameplay]\\chat\\node_modules\\@types\\node\\readline.d.ts","stats":{"mtime":1650228322000,"size":7330,"inode":1125899906885181}},{"name":"D:\\FXServer\\youtube\\resources\\[gameplay]\\chat\\node_modules\\@types\\node\\repl.d.ts","stats":{"mtime":1650228322000,"size":17874,"inode":1125899906885184}},{"name":"D:\\FXServer\\youtube\\resources\\[gameplay]\\chat\\node_modules\\@types\\node\\stream.d.ts","stats":{"mtime":1650228322000,"size":18986,"inode":1125899906885185}},{"name":"D:\\FXServer\\youtube\\resources\\[gameplay]\\chat\\node_modules\\@types\\node\\string_decoder.d.ts","stats":{"mtime":1650228322000,"size":185,"inode":1125899906885187}},{"name":"D:\\FXServer\\youtube\\resources\\[gameplay]\\chat\\node_modules\\@types\\node\\timers.d.ts","stats":{"mtime":1650228322000,"size":826,"inode":1125899906885188}},{"name":"D:\\FXServer\\youtube\\resources\\[gameplay]\\chat\\node_modules\\@types\\node\\tls.d.ts","stats":{"mtime":1650228322000,"size":37312,"inode":1125899906885189}},{"name":"D:\\FXServer\\youtube\\resources\\[gameplay]\\chat\\node_modules\\@types\\node\\trace_events.d.ts","stats":{"mtime":1650228322000,"size":2113,"inode":1125899906885192}},{"name":"D:\\FXServer\\youtube\\resources\\[gameplay]\\chat\\node_modules\\@types\\node\\ts3.2\\fs.d.ts","stats":{"mtime":1650228322000,"size":1088,"inode":1125899906885253}},{"name":"D:\\FXServer\\youtube\\resources\\[gameplay]\\chat\\node_modules\\@types\\node\\ts3.2\\globals.d.ts","stats":{"mtime":1650228322000,"size":640,"inode":1125899906885257}},{"name":"D:\\FXServer\\youtube\\resources\\[gameplay]\\chat\\node_modules\\@types\\node\\ts3.2\\index.d.ts","stats":{"mtime":1650228322000,"size":591,"inode":1125899906885266}},{"name":"D:\\FXServer\\youtube\\resources\\[gameplay]\\chat\\node_modules\\@types\\node\\ts3.2\\util.d.ts","stats":{"mtime":1650228322000,"size":280,"inode":1125899906885284}},{"name":"D:\\FXServer\\youtube\\resources\\[gameplay]\\chat\\node_modules\\@types\\node\\tty.d.ts","stats":{"mtime":1650228322000,"size":2442,"inode":1125899906885196}},{"name":"D:\\FXServer\\youtube\\resources\\[gameplay]\\chat\\node_modules\\@types\\node\\url.d.ts","stats":{"mtime":1650228322000,"size":3828,"inode":1125899906885197}},{"name":"D:\\FXServer\\youtube\\resources\\[gameplay]\\chat\\node_modules\\@types\\node\\util.d.ts","stats":{"mtime":1650228322000,"size":12173,"inode":1125899906885207}},{"name":"D:\\FXServer\\youtube\\resources\\[gameplay]\\chat\\node_modules\\@types\\node\\v8.d.ts","stats":{"mtime":1650228322000,"size":6769,"inode":1125899906885217}},{"name":"D:\\FXServer\\youtube\\resources\\[gameplay]\\chat\\node_modules\\@types\\node\\vm.d.ts","stats":{"mtime":1650228322000,"size":5730,"inode":1125899906885229}},{"name":"D:\\FXServer\\youtube\\resources\\[gameplay]\\chat\\node_modules\\@types\\node\\worker_threads.d.ts","stats":{"mtime":1650228322000,"size":8461,"inode":1125899906885230}},{"name":"D:\\FXServer\\youtube\\resources\\[gameplay]\\chat\\node_modules\\@types\\node\\zlib.d.ts","stats":{"mtime":1650228322000,"size":12182,"inode":1125899906885231}},{"name":"D:\\FXServer\\youtube\\resources\\[gameplay]\\chat\\node_modules\\lodash\\lodash.js","stats":{"mtime":1650228312000,"size":540512,"inode":1125899906900700}},{"name":"D:\\FXServer\\youtube\\resources\\[gameplay]\\chat\\node_modules\\typescript\\lib\\lib.dom.d.ts","stats":{"mtime":1650228314000,"size":840098,"inode":562949953488453}},{"name":"D:\\FXServer\\youtube\\resources\\[gameplay]\\chat\\node_modules\\typescript\\lib\\lib.es2015.collection.d.ts","stats":{"mtime":1650228314000,"size":2910,"inode":562949953488455}},{"name":"D:\\FXServer\\youtube\\resources\\[gameplay]\\chat\\node_modules\\typescript\\lib\\lib.es2015.core.d.ts","stats":{"mtime":1650228314000,"size":20397,"inode":562949953488456}},{"name":"D:\\FXServer\\youtube\\resources\\[gameplay]\\chat\\node_modules\\typescript\\lib\\lib.es2015.d.ts","stats":{"mtime":1650228314000,"size":1261,"inode":562949953488457}},{"name":"D:\\FXServer\\youtube\\resources\\[gameplay]\\chat\\node_modules\\typescript\\lib\\lib.es2015.generator.d.ts","stats":{"mtime":1650228314000,"size":2621,"inode":562949953488458}},{"name":"D:\\FXServer\\youtube\\resources\\[gameplay]\\chat\\node_modules\\typescript\\lib\\lib.es2015.iterable.d.ts","stats":{"mtime":1650228314000,"size":15415,"inode":562949953488459}},{"name":"D:\\FXServer\\youtube\\resources\\[gameplay]\\chat\\node_modules\\typescript\\lib\\lib.es2015.promise.d.ts","stats":{"mtime":1650228314000,"size":7362,"inode":562949953488460}},{"name":"D:\\FXServer\\youtube\\resources\\[gameplay]\\chat\\node_modules\\typescript\\lib\\lib.es2015.proxy.d.ts","stats":{"mtime":1650228314000,"size":1984,"inode":562949953488461}},{"name":"D:\\FXServer\\youtube\\resources\\[gameplay]\\chat\\node_modules\\typescript\\lib\\lib.es2015.reflect.d.ts","stats":{"mtime":1650228314000,"size":1929,"inode":562949953488462}},{"name":"D:\\FXServer\\youtube\\resources\\[gameplay]\\chat\\node_modules\\typescript\\lib\\lib.es2015.symbol.d.ts","stats":{"mtime":1650228314000,"size":1685,"inode":562949953488463}},{"name":"D:\\FXServer\\youtube\\resources\\[gameplay]\\chat\\node_modules\\typescript\\lib\\lib.es2015.symbol.wellknown.d.ts","stats":{"mtime":1650228314000,"size":10555,"inode":562949953488464}},{"name":"D:\\FXServer\\youtube\\resources\\[gameplay]\\chat\\node_modules\\typescript\\lib\\lib.es2016.array.include.d.ts","stats":{"mtime":1650228314000,"size":4968,"inode":562949953488465}},{"name":"D:\\FXServer\\youtube\\resources\\[gameplay]\\chat\\node_modules\\typescript\\lib\\lib.es2016.d.ts","stats":{"mtime":1650228314000,"size":939,"inode":562949953488466}},{"name":"D:\\FXServer\\youtube\\resources\\[gameplay]\\chat\\node_modules\\typescript\\lib\\lib.es2017.d.ts","stats":{"mtime":1650228314000,"size":1099,"inode":562949953488468}},{"name":"D:\\FXServer\\youtube\\resources\\[gameplay]\\chat\\node_modules\\typescript\\lib\\lib.es2017.intl.d.ts","stats":{"mtime":1650228314000,"size":1266,"inode":562949953488470}},{"name":"D:\\FXServer\\youtube\\resources\\[gameplay]\\chat\\node_modules\\typescript\\lib\\lib.es2017.object.d.ts","stats":{"mtime":1650228314000,"size":2492,"inode":562949953488471}},{"name":"D:\\FXServer\\youtube\\resources\\[gameplay]\\chat\\node_modules\\typescript\\lib\\lib.es2017.sharedmemory.d.ts","stats":{"mtime":1650228314000,"size":6270,"inode":562949953488472}},{"name":"D:\\FXServer\\youtube\\resources\\[gameplay]\\chat\\node_modules\\typescript\\lib\\lib.es2017.string.d.ts","stats":{"mtime":1650228314000,"size":2415,"inode":562949953488473}},{"name":"D:\\FXServer\\youtube\\resources\\[gameplay]\\chat\\node_modules\\typescript\\lib\\lib.es2017.typedarrays.d.ts","stats":{"mtime":1650228314000,"size":1470,"inode":562949953488474}},{"name":"D:\\FXServer\\youtube\\resources\\[gameplay]\\chat\\node_modules\\typescript\\lib\\lib.es2018.asyncgenerator.d.ts","stats":{"mtime":1650228314000,"size":2756,"inode":562949953488475}},{"name":"D:\\FXServer\\youtube\\resources\\[gameplay]\\chat\\node_modules\\typescript\\lib\\lib.es2018.asynciterable.d.ts","stats":{"mtime":1650228314000,"size":1780,"inode":562949953488476}},{"name":"D:\\FXServer\\youtube\\resources\\[gameplay]\\chat\\node_modules\\typescript\\lib\\lib.es2018.d.ts","stats":{"mtime":1650228314000,"size":1104,"inode":562949953488477}},{"name":"D:\\FXServer\\youtube\\resources\\[gameplay]\\chat\\node_modules\\typescript\\lib\\lib.es2018.intl.d.ts","stats":{"mtime":1650228314000,"size":1853,"inode":562949953488479}},{"name":"D:\\FXServer\\youtube\\resources\\[gameplay]\\chat\\node_modules\\typescript\\lib\\lib.es2018.promise.d.ts","stats":{"mtime":1650228314000,"size":1374,"inode":562949953488480}},{"name":"D:\\FXServer\\youtube\\resources\\[gameplay]\\chat\\node_modules\\typescript\\lib\\lib.es2018.regexp.d.ts","stats":{"mtime":1650228314000,"size":1255,"inode":562949953488481}},{"name":"D:\\FXServer\\youtube\\resources\\[gameplay]\\chat\\node_modules\\typescript\\lib\\lib.es2020.bigint.d.ts","stats":{"mtime":1650228314000,"size":31017,"inode":562949953488488}},{"name":"D:\\FXServer\\youtube\\resources\\[gameplay]\\chat\\node_modules\\typescript\\lib\\lib.es5.d.ts","stats":{"mtime":1650228314000,"size":208502,"inode":562949953488494}},{"name":"D:\\FXServer\\youtube\\resources\\[gameplay]\\chat\\node_modules\\typescript\\lib\\lib.esnext.intl.d.ts","stats":{"mtime":1650228314000,"size":1266,"inode":562949953488501}},{"name":"D:\\FXServer\\youtube\\resources\\[gameplay]\\chat\\node_modules\\vue-loader\\lib\\runtime\\componentNormalizer.js","stats":{"mtime":1650228314000,"size":2690,"inode":562949953489333}},{"name":"D:\\FXServer\\youtube\\resources\\[gameplay]\\chat\\node_modules\\vue\\dist\\vue.runtime.esm.js","stats":{"mtime":1650228310000,"size":227323,"inode":562949953489046}},{"name":"D:\\FXServer\\youtube\\resources\\[gameplay]\\chat\\node_modules\\vue\\types\\index.d.ts","stats":{"mtime":1650228310000,"size":600,"inode":562949953489295}},{"name":"D:\\FXServer\\youtube\\resources\\[gameplay]\\chat\\node_modules\\vue\\types\\options.d.ts","stats":{"mtime":1650228310000,"size":6992,"inode":562949953489296}},{"name":"D:\\FXServer\\youtube\\resources\\[gameplay]\\chat\\node_modules\\vue\\types\\plugin.d.ts","stats":{"mtime":1650228310000,"size":201,"inode":562949953489297}},{"name":"D:\\FXServer\\youtube\\resources\\[gameplay]\\chat\\node_modules\\vue\\types\\umd.d.ts","stats":{"mtime":1650228310000,"size":2154,"inode":562949953489298}},{"name":"D:\\FXServer\\youtube\\resources\\[gameplay]\\chat\\node_modules\\vue\\types\\vnode.d.ts","stats":{"mtime":1650228310000,"size":2111,"inode":562949953489299}},{"name":"D:\\FXServer\\youtube\\resources\\[gameplay]\\chat\\node_modules\\vue\\types\\vue.d.ts","stats":{"mtime":1650228310000,"size":6619,"inode":562949953489300}},{"name":"D:\\FXServer\\youtube\\resources\\[system]\\[builders]\\webpack\\node_modules\\process\\browser.js","stats":{"mtime":1650228306000,"size":5418,"inode":562949953493054}},{"name":"D:\\FXServer\\youtube\\resources\\[system]\\[builders]\\webpack\\node_modules\\setimmediate\\setImmediate.js","stats":{"mtime":1650228306000,"size":6475,"inode":562949953493366}},{"name":"D:\\FXServer\\youtube\\resources\\[system]\\[builders]\\webpack\\node_modules\\timers-browserify\\main.js","stats":{"mtime":1650228306000,"size":2022,"inode":562949953493668}},{"name":"D:\\FXServer\\youtube\\resources\\[system]\\[builders]\\webpack\\node_modules\\webpack\\buildin\\global.js","stats":{"mtime":1650228304000,"size":472,"inode":562949953494009}},{"name":"D:\\FXServer\\youtube\\resources\\[system]\\[builders]\\webpack\\node_modules\\webpack\\buildin\\module.js","stats":{"mtime":1650228304000,"size":497,"inode":562949953494011}}]